pfcm/__init__.py
pfcm/cli.py
pfcm/pfcm.py
pfcm-0.1.3.dist-info/LICENSE
pfcm-0.1.3.dist-info/METADATA
pfcm-0.1.3.dist-info/WHEEL
pfcm-0.1.3.dist-info/entry_points.txt
pfcm-0.1.3.dist-info/top_level.txt
pfcm-0.1.3.dist-info/RECORD
