Metadata-Version: 2.1
Name: pfcm
Version: 0.1.3
Summary: another fcm wrapper in python
Home-page: https://github.com/jiamo/pfcm
Author: jiamo
Author-email: life.130815@gmail.com
License: MIT
Keywords: pfcm
Platform: UNKNOWN
Classifier: Development Status :: 2 - Pre-Alpha
Classifier: Intended Audience :: Developers
Classifier: Natural Language :: English
Classifier: Programming Language :: Python :: 3.6
Requires-Dist: click (>=6.0)
Requires-Dist: google-api-python-client (>=1.6.4)
Requires-Dist: oauth2client (>=4.1.2)
Requires-Dist: requests
Requires-Dist: PyYAML
Requires-Dist: aiohttp
